mmringbuffer/__init__.py
mmringbuffer/collections.py
mmringbuffer/constants.py
mmringbuffer-0.0.2.dist-info/DESCRIPTION.rst
mmringbuffer-0.0.2.dist-info/METADATA
mmringbuffer-0.0.2.dist-info/metadata.json
mmringbuffer-0.0.2.dist-info/RECORD
mmringbuffer-0.0.2.dist-info/top_level.txt
mmringbuffer-0.0.2.dist-info/WHEEL
mmringbuffer-0.0.2.dist-info/zip-safe
tests/__init__.py
tests/test_collections.py
