Metadata-Version: 2.0
Name: mmringbuffer
Version: 0.0.2
Summary: A memory-mapped ring buffer in Python
Home-page: https://github.com/whiskerlabs/mmringbuffer
Author: Evan Meagher
Author-email: evan@whiskerlabs.com
License: MIT
Keywords: mmap memory mapped ring circular buffer
Platform: UNKNOWN
Classifier: Development Status :: 3 - Alpha
Classifier: Intended Audience :: Developers
Classifier: License :: OSI Approved :: MIT License
Classifier: Operating System :: OS Independent
Classifier: Programming Language :: Python
